postgres_lock/__init__.py
postgres_lock/asyncpg.py
postgres_lock/errors.py
postgres_lock/lock.py
postgres_lock/psycopg2.py
postgres_lock/psycopg3.py
postgres_lock/py.typed
postgres_lock/sqlalchemy.py
postgres_lock-0.1.4.dist-info/LICENSE
postgres_lock-0.1.4.dist-info/METADATA
postgres_lock-0.1.4.dist-info/WHEEL
postgres_lock-0.1.4.dist-info/RECORD
