Metadata-Version: 2.1
Name: postgres-lock
Version: 0.1.4
Summary: Lock mechanism implemented with Postgres advisory locks.
Home-page: https://github.com/seankerr/py-postgres-lock
License: BSD-3-Clause
Keywords: postgres,postgresql,distributed,lock
Author: Sean Kerr
Author-email: sean@code-box.org
Requires-Python: >=3.7,<4.0
Classifier: License :: OSI Approved :: BSD License
Classifier: Programming Language :: Python :: 3
Classifier: Programming Language :: Python :: 3.7
Classifier: Programming Language :: Python :: 3.8
Classifier: Programming Language :: Python :: 3.9
Classifier: Programming Language :: Python :: 3.10
Classifier: Programming Language :: Python :: 3.11
Project-URL: Repository, https://github.com/seankerr/py-postgres-lock
